Categorizer/Categorizer.py
Categorizer/__init__.py
Merkurial_Categorizer-0.0.2.dist-info/LICENSE
Merkurial_Categorizer-0.0.2.dist-info/METADATA
Merkurial_Categorizer-0.0.2.dist-info/WHEEL
Merkurial_Categorizer-0.0.2.dist-info/top_level.txt
Merkurial_Categorizer-0.0.2.dist-info/RECORD
