Metadata-Version: 2.1
Name: Merkurial-Categorizer
Version: 0.0.2
Summary: Categorizes Text Based On A Dictionary Of Lists Of Strings And Callbacks If Needed. Essentially A Template Is Created And Then It Does Its Work. It Then Moves The File Or File Into A Directory And Accompanying Sub-Directories Based From The Root Directory Provided, Followed By The Categories Decided Upon, And Lastly The Final Directory With All Its Contents Will Be In Placed Into The Last Sub Category.
Author-email: Brandon Marcure <brandon@merkurialphoenix.com>
Project-URL: Homepage, https://github.com/ArisenPhoenix/Categorizer
Project-URL: Bug Tracker, https://github.com/ArisenPhoenix/Categorizer/issues
Classifier: Programming Language :: Python :: 3
Classifier: License :: OSI Approved :: GNU General Public License (GPL)
Classifier: Operating System :: OS Independent
Requires-Python: >=3.10
License-File: LICENSE
Requires-Dist: Merkurial-FileUtils >=0.0.0
